jupyterlab_scenes/__init__.py
jupyterlab_scenes/_version.py
jupyterlab_scenes/labextension/build_log.json
jupyterlab_scenes/labextension/package.json
jupyterlab_scenes/labextension/schemas/jupyterlab_scenes/package.json.orig
jupyterlab_scenes/labextension/schemas/jupyterlab_scenes/plugin.json
jupyterlab_scenes/labextension/static/lib_index_js.0aa35e0458ae63cde8ee.js
jupyterlab_scenes/labextension/static/lib_index_js.0aa35e0458ae63cde8ee.js.map
jupyterlab_scenes/labextension/static/lib_index_js.464c8e8f3b11e19e4131.js
jupyterlab_scenes/labextension/static/lib_index_js.464c8e8f3b11e19e4131.js.map
jupyterlab_scenes/labextension/static/lib_index_js.78369b03b66fdbe5eac3.js
jupyterlab_scenes/labextension/static/lib_index_js.78369b03b66fdbe5eac3.js.map
jupyterlab_scenes/labextension/static/lib_index_js.96021e5ad2af4f2e5eba.js
jupyterlab_scenes/labextension/static/lib_index_js.96021e5ad2af4f2e5eba.js.map
jupyterlab_scenes/labextension/static/lib_index_js.96d057f53bf6361735d7.js
jupyterlab_scenes/labextension/static/lib_index_js.96d057f53bf6361735d7.js.map
jupyterlab_scenes/labextension/static/lib_index_js.a4e6c74e170d0f4c67ca.js
jupyterlab_scenes/labextension/static/lib_index_js.a4e6c74e170d0f4c67ca.js.map
jupyterlab_scenes/labextension/static/lib_index_js.dbc5e6bf4d36e92df0a4.js
jupyterlab_scenes/labextension/static/lib_index_js.dbc5e6bf4d36e92df0a4.js.map
jupyterlab_scenes/labextension/static/lib_index_js.f465585239b61c842ee4.js
jupyterlab_scenes/labextension/static/lib_index_js.f465585239b61c842ee4.js.map
jupyterlab_scenes/labextension/static/lib_index_js.fe968cb4f1e9e644c518.js
jupyterlab_scenes/labextension/static/lib_index_js.fe968cb4f1e9e644c518.js.map
jupyterlab_scenes/labextension/static/remoteEntry.080c207a518f60ccdd6f.js.map
jupyterlab_scenes/labextension/static/remoteEntry.2cbe9eadc8c75dd93db6.js.map
jupyterlab_scenes/labextension/static/remoteEntry.2f951cd84781e8cbc7cc.js.map
jupyterlab_scenes/labextension/static/remoteEntry.5c3d93e2489ccdb015f2.js.map
jupyterlab_scenes-2.0.0.dist-info/LICENSE
jupyterlab_scenes-2.0.0.dist-info/METADATA
jupyterlab_scenes-2.0.0.dist-info/WHEEL
jupyterlab_scenes-2.0.0.dist-info/top_level.txt
jupyterlab_scenes-2.0.0.dist-info/RECORD
