Metadata-Version: 2.1
Name: jupyterlab-scenes
Version: 2.0.0
Summary: Define subsets of code cells as scenes and execute them.
Home-page: https://github.com/schmidi314/jupyterlab_scenes
Author: Manuel Schmidt
Author-email: Manuel.J.Schmidt@t-online.de
License: BSD-3-Clause
Keywords: Jupyter,JupyterLab,JupyterLab4
Platform: Linux
Platform: Mac OS X
Platform: Windows
Classifier: License :: OSI Approved :: BSD License
Classifier: Programming Language :: Python
Classifier: Programming Language :: Python :: 3
Classifier: Programming Language :: Python :: 3.6
Classifier: Programming Language :: Python :: 3.7
Classifier: Programming Language :: Python :: 3.8
Classifier: Programming Language :: Python :: 3.9
Classifier: Framework :: Jupyter
Classifier: Framework :: Jupyter :: JupyterLab
Classifier: Framework :: Jupyter :: JupyterLab :: 4
Classifier: Framework :: Jupyter :: JupyterLab :: Extensions
Classifier: Framework :: Jupyter :: JupyterLab :: Extensions :: Prebuilt
Requires-Python: >=3.6
License-File: LICENSE
Requires-Dist: jupyterlab (>=4.0.0a34)
